AUTHORS.rst
CONTRIBUTING.rst
HISTORY.rst
LICENSE
MANIFEST.in
README.rst
setup.cfg
setup.py
docs/Makefile
docs/authors.rst
docs/conf.py
docs/contributing.rst
docs/history.rst
docs/index.rst
docs/installation.rst
docs/make.bat
docs/readme.rst
docs/usage.rst
pypuck/__init__.py
pypuck/__main__.py
pypuck/exceptions.py
pypuck/pypuck.py
pypuck.egg-info/PKG-INFO
pypuck.egg-info/SOURCES.txt
pypuck.egg-info/dependency_links.txt
pypuck.egg-info/entry_points.txt
pypuck.egg-info/not-zip-safe
pypuck.egg-info/requires.txt
pypuck.egg-info/top_level.txt
tests/__init__.py
tests/test_pypuck.py